validiz/__init__.py
validiz/_base_client.py
validiz/_exceptions.py
validiz/_response_handling.py
validiz/_schema.py
validiz/async_client.py
validiz/client.py
validiz-1.1.1.dist-info/METADATA
validiz-1.1.1.dist-info/WHEEL
validiz-1.1.1.dist-info/top_level.txt
validiz-1.1.1.dist-info/RECORD
