Metadata-Version: 2.4
Name: validiz
Version: 1.1.1
Summary: A Python client library for the Validiz Email Validation API
Author-email: Shehryar Sohail <shehryardev@paklogics.com>
License: MIT
Project-URL: Homepage, https://github.com/shehryardev/validiz-python
Project-URL: Issues, https://github.com/shehryardev/validiz-python/issues
Keywords: email,validation,api,client,async
Classifier: Development Status :: 5 - Production/Stable
Classifier: Intended Audience :: Developers
Classifier: License :: OSI Approved :: MIT License
Classifier: Programming Language :: Python :: 3
Classifier: Programming Language :: Python :: 3.9
Classifier: Programming Language :: Python :: 3.10
Classifier: Programming Language :: Python :: 3.11
Classifier: Topic :: Software Development :: Libraries :: Python Modules
Requires-Python: >=3.9
Requires-Dist: requests>=2.25.0
Requires-Dist: aiohttp>=3.10.0
Requires-Dist: pandas>=2.0.0
